sget/__init__.py
sget/api.py
sget/config.py
sget/main.py
sget/snippet.py
sget/storage.py
sget/tty.py
sget/prompt/__init__.py
sget/prompt/prompt.py
sget/prompt/search.py
sget/prompt/template.py
sget-0.1.0.dist-info/LICENSE
sget-0.1.0.dist-info/METADATA
sget-0.1.0.dist-info/WHEEL
sget-0.1.0.dist-info/entry_points.txt
sget-0.1.0.dist-info/top_level.txt
sget-0.1.0.dist-info/RECORD
