Metadata-Version: 2.1
Name: sget
Version: 0.1.0
Summary: A simple snippet manager.
Home-page: https://github.com/ONordander/sget
Author: Otto Nordander
Author-email: otto.nordander@gmail.com
License: APACHE
Platform: UNKNOWN
Classifier: License :: OSI Approved :: Apache Software License
Classifier: Programming Language :: Python
Classifier: Programming Language :: Python :: 3.4
Classifier: Programming Language :: Python :: 3.5
Classifier: Programming Language :: Python :: 3.6
Classifier: Programming Language :: Python :: 3.7
Requires-Python: >=3.4.0
Requires-Dist: Click (==7.0)
Requires-Dist: Pyperclip (==1.7.0)
Requires-Dist: toml (==0.10.0)
Requires-Dist: prompt-toolkit (==2.0.8)
